main.py
weatherapi_mcp_server-0.1.0.dist-info/licenses/LICENSE
weatherapi_mcp_server-0.1.0.dist-info/METADATA
weatherapi_mcp_server-0.1.0.dist-info/WHEEL
weatherapi_mcp_server-0.1.0.dist-info/entry_points.txt
weatherapi_mcp_server-0.1.0.dist-info/top_level.txt
weatherapi_mcp_server-0.1.0.dist-info/RECORD
